{
  "Version": 1,
  "Name": "rangbaer_3",
  "ModelID": "405a0860bc154f63a284eb3f6f9472c0",
  "FileReferences": {
    "Icon": "icon_rangbaer_3.png",
    "Model": "rangbaer_3.model3.json",
    "IdleAnimation": "",
    "IdleAnimationWhenTrackingLost": "idle.motion3.json"
  },
  "ModelSaveMetadata": {
    "LastSavedVTubeStudioVersion": "1.17.0",
    "LastSavedPlatform": "Steam",
    "LastSavedDateUTC": "Wednesday, 23 February 2022, 15:23:51",
    "LastSavedDateLocalTime": "Wednesday, 23 February 2022, 23:23:51",
    "LastSavedDateUnixMillisecondTimestamp": "1645629831909"
  },
  "SavedModelPosition": {
    "Position": {
      "x": 0.0,
      "y": 0.0,
      "z": 0.0
    },
    "Rotation": {
      "x": 0.0,
      "y": 0.0,
      "z": 0.0,
      "w": 1.0
    },
    "Scale": {
      "x": 0.1,
      "y": 0.1,
      "z": 1.0
    }
  },
  "ModelPositionMovement": {
    "Use": true,
    "X": 6,
    "Y": 8,
    "Z": 11,
    "SmoothingX": 10,
    "SmoothingY": 10,
    "SmoothingZ": 10
  },
  "PhysicsSettings": {
    "Use": true,
    "UseLegacyPhysics": false,
    "Live2DPhysicsFPS": 3,
    "PhysicsStrength": 50,
    "WindStrength": 0
  },
  "GeneralSettings": {
    "TimeUntilTrackingLostIdleAnimation": 0.0
  },
  "ParameterSettings": [],
  "Hotkeys": [
    {
      "HotkeyID": "f9453e0949094b4ca04ab432b3fd7c57",
      "Name": "login",
      "Action": "TriggerAnimation",
      "File": "login.motion3.json",
      "Position": {
        "X": 0.0,
        "Y": 0.0,
        "Z": 0.0,
        "Rotation": 0.0
      },
      "ColorOverlay": {
        "On": false,
        "Display": -1,
        "WindowName": "",
        "IncludeLeft": false,
        "IncludeMid": false,
        "IncludeRight": false,
        "BaseValue": 0,
        "OverlayValue": 0,
        "Smoothing": 0,
        "IncludeItems": false
      },
      "HandGestureSettings": {
        "GestureLeft": "",
        "GestureRight": "",
        "GestureCombinator": "AND",
        "AllowMirroredGesture": false,
        "DeactivateExpWhenGestureNotDetected": false,
        "SecondsUntilDetection": 0.5,
        "SecondsDetected": 0.0,
        "PercentDetected": 0.0
      },
      "Triggers": {
        "Trigger1": "RightControl",
        "Trigger2": "Numpad0",
        "ScreenButton": -1
      },
      "IsGlobal": true,
      "IsActive": true,
      "Minimized": false,
      "StopsOnLastFrame": false,
      "DeactivateAfterKeyUp": false,
      "DeactivateAfterSeconds": false,
      "DeactivateAfterSecondsAmount": 10.0,
      "FadeSecondsAmount": 0.5,
      "OnScreenHotkeyColor": {
        "r": 1.0,
        "g": 1.0,
        "b": 1.0,
        "a": 1.0
      }
    },
    {
      "HotkeyID": "cc64429193c544b0a0362cb52c001286",
      "Name": "main_1",
      "Action": "TriggerAnimation",
      "File": "main_1.motion3.json",
      "Position": {
        "X": 0.0,
        "Y": 0.0,
        "Z": 0.0,
        "Rotation": 0.0
      },
      "ColorOverlay": {
        "On": false,
        "Display": -1,
        "WindowName": "",
        "IncludeLeft": false,
        "IncludeMid": false,
        "IncludeRight": false,
        "BaseValue": 0,
        "OverlayValue": 0,
        "Smoothing": 0,
        "IncludeItems": false
      },
      "HandGestureSettings": {
        "GestureLeft": "",
        "GestureRight": "",
        "GestureCombinator": "AND",
        "AllowMirroredGesture": false,
        "DeactivateExpWhenGestureNotDetected": false,
        "SecondsUntilDetection": 0.5,
        "SecondsDetected": 0.0,
        "PercentDetected": 0.0
      },
      "Triggers": {
        "Trigger1": "RightControl",
        "Trigger2": "Numpad1",
        "ScreenButton": -1
      },
      "IsGlobal": true,
      "IsActive": true,
      "Minimized": false,
      "StopsOnLastFrame": false,
      "DeactivateAfterKeyUp": false,
      "DeactivateAfterSeconds": false,
      "DeactivateAfterSecondsAmount": 10.0,
      "FadeSecondsAmount": 0.5,
      "OnScreenHotkeyColor": {
        "r": 1.0,
        "g": 1.0,
        "b": 1.0,
        "a": 1.0
      }
    },
    {
      "HotkeyID": "70eb66376a3b439abcad7347af7981de",
      "Name": "main_2",
      "Action": "TriggerAnimation",
      "File": "main_2.motion3.json",
      "Position": {
        "X": 0.0,
        "Y": 0.0,
        "Z": 0.0,
        "Rotation": 0.0
      },
      "ColorOverlay": {
        "On": false,
        "Display": -1,
        "WindowName": "",
        "IncludeLeft": false,
        "IncludeMid": false,
        "IncludeRight": false,
        "BaseValue": 0,
        "OverlayValue": 0,
        "Smoothing": 0,
        "IncludeItems": false
      },
      "HandGestureSettings": {
        "GestureLeft": "",
        "GestureRight": "",
        "GestureCombinator": "AND",
        "AllowMirroredGesture": false,
        "DeactivateExpWhenGestureNotDetected": false,
        "SecondsUntilDetection": 0.5,
        "SecondsDetected": 0.0,
        "PercentDetected": 0.0
      },
      "Triggers": {
        "Trigger1": "RightControl",
        "Trigger2": "Numpad2",
        "ScreenButton": -1
      },
      "IsGlobal": true,
      "IsActive": true,
      "Minimized": false,
      "StopsOnLastFrame": false,
      "DeactivateAfterKeyUp": false,
      "DeactivateAfterSeconds": false,
      "DeactivateAfterSecondsAmount": 10.0,
      "FadeSecondsAmount": 0.5,
      "OnScreenHotkeyColor": {
        "r": 1.0,
        "g": 1.0,
        "b": 1.0,
        "a": 1.0
      }
    },
    {
      "HotkeyID": "9a2877a0e3dc4a55b24182df4f6f86a4",
      "Name": "main_3",
      "Action": "TriggerAnimation",
      "File": "main_3.motion3.json",
      "Position": {
        "X": 0.0,
        "Y": 0.0,
        "Z": 0.0,
        "Rotation": 0.0
      },
      "ColorOverlay": {
        "On": false,
        "Display": -1,
        "WindowName": "",
        "IncludeLeft": false,
        "IncludeMid": false,
        "IncludeRight": false,
        "BaseValue": 0,
        "OverlayValue": 0,
        "Smoothing": 0,
        "IncludeItems": false
      },
      "HandGestureSettings": {
        "GestureLeft": "",
        "GestureRight": "",
        "GestureCombinator": "AND",
        "AllowMirroredGesture": false,
        "DeactivateExpWhenGestureNotDetected": false,
        "SecondsUntilDetection": 0.5,
        "SecondsDetected": 0.0,
        "PercentDetected": 0.0
      },
      "Triggers": {
        "Trigger1": "RightControl",
        "Trigger2": "Numpad3",
        "ScreenButton": -1
      },
      "IsGlobal": true,
      "IsActive": true,
      "Minimized": false,
      "StopsOnLastFrame": false,
      "DeactivateAfterKeyUp": false,
      "DeactivateAfterSeconds": false,
      "DeactivateAfterSecondsAmount": 10.0,
      "FadeSecondsAmount": 0.5,
      "OnScreenHotkeyColor": {
        "r": 1.0,
        "g": 1.0,
        "b": 1.0,
        "a": 1.0
      }
    },
    {
      "HotkeyID": "221e864aa42d473f81e7ed1108cf55d5",
      "Name": "complete",
      "Action": "TriggerAnimation",
      "File": "complete.motion3.json",
      "Position": {
        "X": 0.0,
        "Y": 0.0,
        "Z": 0.0,
        "Rotation": 0.0
      },
      "ColorOverlay": {
        "On": false,
        "Display": -1,
        "WindowName": "",
        "IncludeLeft": false,
        "IncludeMid": false,
        "IncludeRight": false,
        "BaseValue": 0,
        "OverlayValue": 0,
        "Smoothing": 0,
        "IncludeItems": false
      },
      "HandGestureSettings": {
        "GestureLeft": "",
        "GestureRight": "",
        "GestureCombinator": "AND",
        "AllowMirroredGesture": false,
        "DeactivateExpWhenGestureNotDetected": false,
        "SecondsUntilDetection": 0.5,
        "SecondsDetected": 0.0,
        "PercentDetected": 0.0
      },
      "Triggers": {
        "Trigger1": "RightControl",
        "Trigger2": "Numpad4",
        "ScreenButton": -1
      },
      "IsGlobal": true,
      "IsActive": true,
      "Minimized": false,
      "StopsOnLastFrame": false,
      "DeactivateAfterKeyUp": false,
      "DeactivateAfterSeconds": false,
      "DeactivateAfterSecondsAmount": 10.0,
      "FadeSecondsAmount": 0.5,
      "OnScreenHotkeyColor": {
        "r": 1.0,
        "g": 1.0,
        "b": 1.0,
        "a": 1.0
      }
    },
    {
      "HotkeyID": "c1a57c2bbe434cfb8d813a6b0ed0b382",
      "Name": "effect",
      "Action": "TriggerAnimation",
      "File": "effect.motion3.json",
      "Position": {
        "X": 0.0,
        "Y": 0.0,
        "Z": 0.0,
        "Rotation": 0.0
      },
      "ColorOverlay": {
        "On": false,
        "Display": -1,
        "WindowName": "",
        "IncludeLeft": false,
        "IncludeMid": false,
        "IncludeRight": false,
        "BaseValue": 0,
        "OverlayValue": 0,
        "Smoothing": 0,
        "IncludeItems": false
      },
      "HandGestureSettings": {
        "GestureLeft": "",
        "GestureRight": "",
        "GestureCombinator": "AND",
        "AllowMirroredGesture": false,
        "DeactivateExpWhenGestureNotDetected": false,
        "SecondsUntilDetection": 0.5,
        "SecondsDetected": 0.0,
        "PercentDetected": 0.0
      },
      "Triggers": {
        "Trigger1": "RightControl",
        "Trigger2": "Numpad5",
        "ScreenButton": -1
      },
      "IsGlobal": true,
      "IsActive": true,
      "Minimized": false,
      "StopsOnLastFrame": false,
      "DeactivateAfterKeyUp": false,
      "DeactivateAfterSeconds": false,
      "DeactivateAfterSecondsAmount": 10.0,
      "FadeSecondsAmount": 0.5,
      "OnScreenHotkeyColor": {
        "r": 1.0,
        "g": 1.0,
        "b": 1.0,
        "a": 1.0
      }
    },
    {
      "HotkeyID": "1b7375bec794488aaee504f5b52d3692",
      "Name": "home",
      "Action": "TriggerAnimation",
      "File": "home.motion3.json",
      "Position": {
        "X": 0.0,
        "Y": 0.0,
        "Z": 0.0,
        "Rotation": 0.0
      },
      "ColorOverlay": {
        "On": false,
        "Display": -1,
        "WindowName": "",
        "IncludeLeft": false,
        "IncludeMid": false,
        "IncludeRight": false,
        "BaseValue": 0,
        "OverlayValue": 0,
        "Smoothing": 0,
        "IncludeItems": false
      },
      "HandGestureSettings": {
        "GestureLeft": "",
        "GestureRight": "",
        "GestureCombinator": "AND",
        "AllowMirroredGesture": false,
        "DeactivateExpWhenGestureNotDetected": false,
        "SecondsUntilDetection": 0.5,
        "SecondsDetected": 0.0,
        "PercentDetected": 0.0
      },
      "Triggers": {
        "Trigger1": "RightControl",
        "Trigger2": "Numpad6",
        "ScreenButton": -1
      },
      "IsGlobal": true,
      "IsActive": true,
      "Minimized": false,
      "StopsOnLastFrame": false,
      "DeactivateAfterKeyUp": false,
      "DeactivateAfterSeconds": false,
      "DeactivateAfterSecondsAmount": 10.0,
      "FadeSecondsAmount": 0.5,
      "OnScreenHotkeyColor": {
        "r": 1.0,
        "g": 1.0,
        "b": 1.0,
        "a": 1.0
      }
    },
    {
      "HotkeyID": "e11ac3d400874019a910bc7c39e90fde",
      "Name": "mission",
      "Action": "TriggerAnimation",
      "File": "mission.motion3.json",
      "Position": {
        "X": 0.0,
        "Y": 0.0,
        "Z": 0.0,
        "Rotation": 0.0
      },
      "ColorOverlay": {
        "On": false,
        "Display": -1,
        "WindowName": "",
        "IncludeLeft": false,
        "IncludeMid": false,
        "IncludeRight": false,
        "BaseValue": 0,
        "OverlayValue": 0,
        "Smoothing": 0,
        "IncludeItems": false
      },
      "HandGestureSettings": {
        "GestureLeft": "",
        "GestureRight": "",
        "GestureCombinator": "AND",
        "AllowMirroredGesture": false,
        "DeactivateExpWhenGestureNotDetected": false,
        "SecondsUntilDetection": 0.5,
        "SecondsDetected": 0.0,
        "PercentDetected": 0.0
      },
      "Triggers": {
        "Trigger1": "RightControl",
        "Trigger2": "Numpad7",
        "ScreenButton": -1
      },
      "IsGlobal": true,
      "IsActive": true,
      "Minimized": false,
      "StopsOnLastFrame": false,
      "DeactivateAfterKeyUp": false,
      "DeactivateAfterSeconds": false,
      "DeactivateAfterSecondsAmount": 10.0,
      "FadeSecondsAmount": 0.5,
      "OnScreenHotkeyColor": {
        "r": 1.0,
        "g": 1.0,
        "b": 1.0,
        "a": 1.0
      }
    },
    {
      "HotkeyID": "7d551b7b88f5485d8e5cc55d67225a62",
      "Name": "mission_complete",
      "Action": "TriggerAnimation",
      "File": "mission_complete.motion3.json",
      "Position": {
        "X": 0.0,
        "Y": 0.0,
        "Z": 0.0,
        "Rotation": 0.0
      },
      "ColorOverlay": {
        "On": false,
        "Display": -1,
        "WindowName": "",
        "IncludeLeft": false,
        "IncludeMid": false,
        "IncludeRight": false,
        "BaseValue": 0,
        "OverlayValue": 0,
        "Smoothing": 0,
        "IncludeItems": false
      },
      "HandGestureSettings": {
        "GestureLeft": "",
        "GestureRight": "",
        "GestureCombinator": "AND",
        "AllowMirroredGesture": false,
        "DeactivateExpWhenGestureNotDetected": false,
        "SecondsUntilDetection": 0.5,
        "SecondsDetected": 0.0,
        "PercentDetected": 0.0
      },
      "Triggers": {
        "Trigger1": "RightControl",
        "Trigger2": "Numpad8",
        "ScreenButton": -1
      },
      "IsGlobal": true,
      "IsActive": true,
      "Minimized": false,
      "StopsOnLastFrame": false,
      "DeactivateAfterKeyUp": false,
      "DeactivateAfterSeconds": false,
      "DeactivateAfterSecondsAmount": 10.0,
      "FadeSecondsAmount": 0.5,
      "OnScreenHotkeyColor": {
        "r": 1.0,
        "g": 1.0,
        "b": 1.0,
        "a": 1.0
      }
    },
    {
      "HotkeyID": "6bdc29a3427a4514a58025293ec136e9",
      "Name": "wedding",
      "Action": "TriggerAnimation",
      "File": "wedding.motion3.json",
      "Position": {
        "X": 0.0,
        "Y": 0.0,
        "Z": 0.0,
        "Rotation": 0.0
      },
      "ColorOverlay": {
        "On": false,
        "Display": -1,
        "WindowName": "",
        "IncludeLeft": false,
        "IncludeMid": false,
        "IncludeRight": false,
        "BaseValue": 0,
        "OverlayValue": 0,
        "Smoothing": 0,
        "IncludeItems": false
      },
      "HandGestureSettings": {
        "GestureLeft": "",
        "GestureRight": "",
        "GestureCombinator": "AND",
        "AllowMirroredGesture": false,
        "DeactivateExpWhenGestureNotDetected": false,
        "SecondsUntilDetection": 0.5,
        "SecondsDetected": 0.0,
        "PercentDetected": 0.0
      },
      "Triggers": {
        "Trigger1": "RightControl",
        "Trigger2": "Numpad9",
        "ScreenButton": -1
      },
      "IsGlobal": true,
      "IsActive": true,
      "Minimized": false,
      "StopsOnLastFrame": false,
      "DeactivateAfterKeyUp": false,
      "DeactivateAfterSeconds": false,
      "DeactivateAfterSecondsAmount": 10.0,
      "FadeSecondsAmount": 0.5,
      "OnScreenHotkeyColor": {
        "r": 1.0,
        "g": 1.0,
        "b": 1.0,
        "a": 1.0
      }
    }
  ],
  "HotkeySettings": {
    "UseOnScreenHotkeys": false,
    "UseKeyboardHotkeys": true,
    "SendOnScreenHotkeysToPC": true,
    "OnScreenHotkeyAlpha": 75
  },
  "ArtMeshDetails": {
    "ArtMeshesExcludedFromPinning": [],
    "ArtMeshesThatDeleteItemsOnDrop": [],
    "ArtMeshSceneLightingMultipliers": []
  },
  "PhysicsCustomizationSettings": {
    "PhysicsMultipliersPerPhysicsGroup": [],
    "WindMultipliersPerPhysicsGroup": []
  }
}